odoo9_addon_menu_technical_info-9.0.1.0.0-py2.7-nspkg.pth
odoo_addons/menu_technical_info/__openerp__.py
odoo_addons/menu_technical_info/__init__.py
odoo_addons/menu_technical_info/README.rst
odoo_addons/menu_technical_info/views/menu_technical_info_templates.xml
odoo_addons/menu_technical_info/static/src/js/menu_technical_info.js
odoo9_addon_menu_technical_info-9.0.1.0.0.dist-info/top_level.txt
odoo9_addon_menu_technical_info-9.0.1.0.0.dist-info/WHEEL
odoo9_addon_menu_technical_info-9.0.1.0.0.dist-info/RECORD
odoo9_addon_menu_technical_info-9.0.1.0.0.dist-info/metadata.json
odoo9_addon_menu_technical_info-9.0.1.0.0.dist-info/DESCRIPTION.rst
odoo9_addon_menu_technical_info-9.0.1.0.0.dist-info/METADATA
odoo9_addon_menu_technical_info-9.0.1.0.0.dist-info/namespace_packages.txt
